cg_security/__init__.py
cg_security/encrypter.py
cg_security/hasher.py
cg_security/security_exception.py
cg_security-1.0.dist-info/LICENCE
cg_security-1.0.dist-info/METADATA
cg_security-1.0.dist-info/WHEEL
cg_security-1.0.dist-info/top_level.txt
cg_security-1.0.dist-info/RECORD
