Metadata-Version: 2.1
Name: cg-security
Version: 1.0
Summary: UNKNOWN
Home-page: https://github.com/ConnectSW/cg_security
Author: Connect Group, Roberto Mizuuti
Author-email: infra@connect.com.vc
License: UNKNOWN
Platform: UNKNOWN
Classifier: Programming Language :: Python :: 3
Classifier: License :: OSI Approved :: MIT License
Classifier: Operating System :: OS Independent
Requires-Python: >=3.6
Requires-Dist: pycryptodome
